{"message": "product found", "code": 1, "result": {"id": 166, "product_category_id": 2, "name": "솔송주/담솔 선물세트", "thumbnail": "https://sooldamhwa-static-files.s3.ap-northeast-2.amazonaws.com/admin_contents/origin/hi4I-1623375064764-%EB%AA%85%EC%9D%B8%EB%8B%B4%EC%9D%80%EC%84%B8%ED%8A%B8%201%ED%98%B8%20%EC%BC%80%EC%9D%B4%EC%8A%A4%EC%B1%84%EB%A1%9C.png", "real_name": "솔송주/담솔 선물세트", "subtext": "소나무의 향기를 선물해보세요", "tag_string": "#시원한_솔향가득\n#칵테일로_만들기_좋은_담솔", "content": "<p class=\"ql-align-center\"><br></p><p class=\"ql-align-center\"><strong><img src=\"https://sooldamhwa-static-files.s3.ap-northeast-2.amazonaws.com/content_images/contents_images-1623151407549-%EB%8B%B4%EC%86%94%2C-%EC%86%94%EC%86%A1%EC%A3%BC.png\"></strong></p><p class=\"ql-align-center\"><br></p><p class=\"ql-align-center\"><img src=\"https://sooldamhwa-static-files.s3.ap-northeast-2.amazonaws.com/content_images/contents_images-1623374989103-%EB%AA%85%EC%9D%B8%EB%8B%B4%EC%9D%80%EC%84%B8%ED%8A%B8%201%ED%98%B8.png\"></p><p class=\"ql-align-center\"><br></p><p class=\"ql-align-center\"><span style=\"color: rgb(68, 68, 68);\">한국적 정서의 결정체, '소나무' 하면 생각나는 분들에게 선물해보세요</span></p><p class=\"ql-align-center\"><br></p><p class=\"ql-align-center\"><strong class=\"ql-size-huge\" style=\"color: rgb(68, 68, 68);\">구성</strong></p><p class=\"ql-align-center\"><br></p><p class=\"ql-align-center\"><br></p><p class=\"ql-align-center\"><br></p><p class=\"ql-align-center\"><strong style=\"color: rgb(68, 68, 68);\">명인담은세트 1호</strong></p><p class=\"ql-align-center\"><br></p><p class=\"ql-align-center\"><strong class=\"ql-size-large\" style=\"color: rgb(102, 163, 224);\"><em>[375ml] 솔송주 13% + 담솔 40%</em></strong></p>", "mobile_content": "<p class=\"ql-align-center\"><strong><img src=\"https://sooldamhwa-static-files.s3.ap-northeast-2.amazonaws.com/content_images/contents_images-1623151407549-%EB%8B%B4%EC%86%94%2C-%EC%86%94%EC%86%A1%EC%A3%BC.png\"></strong></p><p class=\"ql-align-center\"><br></p><p class=\"ql-align-center\"><img src=\"https://sooldamhwa-static-files.s3.ap-northeast-2.amazonaws.com/content_images/contents_images-1623374989103-%EB%AA%85%EC%9D%B8%EB%8B%B4%EC%9D%80%EC%84%B8%ED%8A%B8%201%ED%98%B8.png\"></p><p class=\"ql-align-center\"><br></p><p class=\"ql-align-center\"><span style=\"color: rgb(68, 68, 68);\">한국적 정서의 결정체, '소나무'하면</span></p><p class=\"ql-align-center\"><span style=\"color: rgb(68, 68, 68);\">생각나는 분들에게 선물해보세요</span></p><p class=\"ql-align-center\"><br></p><p class=\"ql-align-center\"><strong class=\"ql-size-huge\">구성</strong></p><p class=\"ql-align-center\"><br></p><p class=\"ql-align-center\"><br></p><p class=\"ql-align-center\"><br></p><p class=\"ql-align-center\"><strong style=\"color: rgb(68, 68, 68);\">명인담은세트 1호</strong></p><p class=\"ql-align-center\"><strong class=\"ql-size-large\" style=\"color: rgb(102, 163, 224);\"><em>[375ml] 솔송주 13% + 담솔 40%</em></strong></p><p class=\"ql-align-center\"><strong>판매가 : 33,000원</strong></p>", "origin_price": 33000, "discount_price": 33000, "is_damhwa_box": 0, "selling_count": 202, "hit_count": 0, "star_rating": "4.8", "status": "active", "star_count": 5, "maker_id": 15, "product_images": [{"id": 6826, "product_id": 166, "image_url": "https://sooldamhwa-static-files.s3.ap-northeast-2.amazonaws.com/admin_contents/origin/hi4I-1623375064764-%EB%AA%85%EC%9D%B8%EB%8B%B4%EC%9D%80%EC%84%B8%ED%8A%B8%201%ED%98%B8%20%EC%BC%80%EC%9D%B4%EC%8A%A4%EC%B1%84%EB%A1%9C.png"}], "product_options": [{"id": 272, "name": "[375ml] 명인담은세트 1호 (솔송주 13%+담솔 40%)", "origin_price": 33000, "discount_price": 33000, "status": "active", "stock": 940, "component_arr": "[{\"product_id\":93,\"real_name\":\"솔송주\"},{\"product_id\":95,\"real_name\":\"담솔\"}]"}], "maker": {"id": 15, "name": "솔송주", "maker_image_url": "https://sooldamhwa-static-files.s3.ap-northeast-2.amazonaws.com/admin_contents/origin/FC1g-1622695043299-sol-song-joo.png", "value": 15, "label": "솔송주", "regular_delivery_price": 3500, "special_delivery_price": 6500, "delivery_note": "2일 이내 배송", "min_total_for_free_delivery": 35000, "official_name": "농업회사법인 (주)솔송주", "ceo_name": "정천상", "email": "solsongju@naver.com", "phone_number": "055-963-8992~3", "address": "경상남도 함양군 지곡면 지곡창촌길 3", "registration_number": "611-81-12872", "report_number": "제2008- 경남함양-17호"}, "sool": null, "tags": [], "product_info": {"id": 195, "product_id": 166, "product_type": "솔송주 : 살균약주 / 담솔: 리큐르", "label": "", "producer": "농업회사법인 (주)솔송주", "location": "경상남도 함양군 지곡면 지곡창촌길 3", "expiration_info": "솔송주 : 상온 보관 가능, 제조일로부터 1년 / 담솔 : 상온 보관 가능, 유통기한 없음", "volume": "375ml", "base_material": "솔송주 : 정제수, 백미(국내산), 국내산 송순 농축액(송순 33%, 정제수 67%) 5.2%, 누룩, 조제종국, 효모 / 담솔 : 정제수, 백미(국내산), 국내산 백미 입국, 국내산 송순 농축액(정제수 67%, 송순33%) 5.43%, 설탕, 누룩, 꿀, 효모, 조제종국, 정제식염, 구연산, 밀함유", "nutrient": "사진 및 상세 설명 확인", "gmo": "해당 사항 없음", "import_note": "해당 사항 없음", "created_at": "2021-05-15T02:27:19.000Z", "updated_at": "2021-06-22T03:20:15.000Z", "destroyTime": null}}}