{"message": "product found", "code": 1, "result": {"id": 352, "product_category_id": 1, "name": "금이산 복숭아 와인", "thumbnail": "https://sooldamhwa-static-files.s3.ap-northeast-2.amazonaws.com/admin_contents/origin/1jU3-1620615612711-%EA%B8%88%EC%9D%B4%EC%82%B0%EB%B3%B5%EC%88%AD%EC%95%84%EC%99%80%EC%9D%B8.jpg", "real_name": "금이산 복숭아 와인", "subtext": "달콤한 복숭아 한가득 들어간 복숭아 와인", "tag_string": "#복숭아로_만든_와인\n#달콤한_백도_한가득", "content": "<p class=\"ql-align-center\"><img src=\"https://sooldamhwa-static-files.s3.ap-northeast-2.amazonaws.com/content_images/contents_images-1621489065404-%EA%B8%88%EC%9D%B4%EC%82%B0%EB%86%8D%EC%9B%90-%EB%B3%B5%EC%88%AD%EC%95%84%EC%99%80%EC%9D%B8-4.png\"></p><p class=\"ql-align-center\"><strong class=\"ql-size-large\">[금이산 복숭아 와인], 어떤 맛을 갖고 있나요?</strong></p><p class=\"ql-align-center\"><br></p><p class=\"ql-align-center\">복숭아씨를 제거한 후 과육만을 사용하여 만든 과실주에요.</p><p class=\"ql-align-center\"><br></p><p class=\"ql-align-center\"><strong style=\"color: rgb(255, 153, 0);\">복숭아 본연의 단맛</strong>을 강하게 느낄 수 있지만</p><p class=\"ql-align-center\"><br></p><p class=\"ql-align-center\">단맛 뒤에 슬며시 올라오는 <strong style=\"color: rgb(255, 153, 0);\">씁쓸한 맛</strong>이 입안을 정리해주어 깔끔하게 즐길 수 있는 술입니다!</p><p class=\"ql-align-center\"><img src=\"https://sooldamhwa-static-files.s3.ap-northeast-2.amazonaws.com/content_images/contents_images-1621489075322-%EA%B8%88%EC%9D%B4%EC%82%B0%EB%86%8D%EC%9B%90-%EB%B3%B5%EC%88%AD%EC%95%84%EC%99%80%EC%9D%B8-2.png\"></p><p class=\"ql-align-center\"><strong class=\"ql-size-large\">[금이산 복숭아 와인], 어떤 음식과 잘 어울리나요?</strong></p><p class=\"ql-align-center\"><br></p><p class=\"ql-align-center\">강한 단맛을 무겁지 않게 즐기고 복숭아의 싱그러운 향을 생동감 있게 즐기기 위해선</p><p class=\"ql-align-center\"><br></p><p class=\"ql-align-center\"><strong style=\"color: rgb(255, 153, 0);\">시원한 상태</strong>로 마시는 것을 추천해 드립니다.</p><p class=\"ql-align-center\"><br></p><p class=\"ql-align-center\">탄산수와 레몬 슬라이스를 넣어 청량감 있는 <strong style=\"color: rgb(255, 153, 0);\">에이드</strong>로 즐겨도 좋고</p><p class=\"ql-align-center\"><br></p><p class=\"ql-align-center\"><strong style=\"color: rgb(255, 153, 0);\">케이크, 마들렌과 같은 디저트류와 달콤하고 부드럽게 즐기기</strong>에도 좋습니다 :)</p><p class=\"ql-align-center\"><br></p><p class=\"ql-align-center\">또한 단맛과 산미가 조화로워 입맛을 돋우기 때문에 <strong style=\"color: rgb(255, 153, 0);\">식전주</strong> 또는</p><p class=\"ql-align-center\"><br></p><p class=\"ql-align-center\">식사를 마무리하고 <strong style=\"color: rgb(255, 153, 0);\">디저트와인</strong>으로 가볍게 즐기시는 걸 추천해드려요.</p><p class=\"ql-align-center\"><img src=\"https://sooldamhwa-static-files.s3.ap-northeast-2.amazonaws.com/content_images/contents_images-1621489080958-%EA%B8%88%EC%9D%B4%EC%82%B0%EB%86%8D%EC%9B%90-%EB%B3%B5%EC%88%AD%EC%95%84%EC%99%80%EC%9D%B8-3.png\"></p><p class=\"ql-align-center\"><strong class=\"ql-size-large\">[금이산 복숭아 와인], 알고 마시면 더 맛있어요!</strong></p><p class=\"ql-align-center\"><br></p><p class=\"ql-align-center\">맛이 좋기로 유명한 세종시 복숭아를 60여 곳의 지역 농가에서 수급하여 빚고 있는데요.</p><p class=\"ql-align-center\"><br></p><p class=\"ql-align-center\">잘 익은 세종시 조치원 복숭아만을 선별하여<strong> </strong><strong style=\"color: rgb(255, 153, 0);\">저온 발효시킨</strong><strong> </strong>와인입니다.</p><p class=\"ql-align-center\"><br></p><p class=\"ql-align-center\"><strong style=\"color: rgb(255, 153, 0);\">인위적인 복숭아향을 사용하지 않아</strong> 자극적이지 않고</p><p class=\"ql-align-center\"><br></p><p class=\"ql-align-center\"><strong style=\"color: rgb(255, 153, 0);\">미세한 필터망</strong> 사용을 통해 복숭아 본연의 풍미를 깔끔하게 경험할 수 있답니다.</p>", "mobile_content": "<p class=\"ql-align-center\"><img src=\"https://sooldamhwa-static-files.s3.ap-northeast-2.amazonaws.com/content_images/contents_images-1621489065404-%EA%B8%88%EC%9D%B4%EC%82%B0%EB%86%8D%EC%9B%90-%EB%B3%B5%EC%88%AD%EC%95%84%EC%99%80%EC%9D%B8-4.png\"></p><p class=\"ql-align-center\"><strong class=\"ql-size-large\">[금이산 복숭아 와인], </strong></p><p class=\"ql-align-center\"><strong class=\"ql-size-large\">어떤 맛을 갖고 있나요?</strong></p><p class=\"ql-align-center\"><br></p><p class=\"ql-align-center\">복숭아씨를 제거한 후 과육만을 사용하여 만든 과실주에요.</p><p class=\"ql-align-center\"><br></p><p class=\"ql-align-center\"><strong style=\"color: rgb(255, 153, 0);\">복숭아 본연의 단맛</strong>을 강하게 느낄 수 있지만</p><p class=\"ql-align-center\"><br></p><p class=\"ql-align-center\">단맛 뒤에 슬며시 올라오는 <strong style=\"color: rgb(255, 153, 0);\">씁쓸한 맛</strong>이 입안을 정리해주어</p><p class=\"ql-align-center\"><br></p><p class=\"ql-align-center\">깔끔하게 즐길 수 있는 술입니다!</p><p class=\"ql-align-center\"><img src=\"https://sooldamhwa-static-files.s3.ap-northeast-2.amazonaws.com/content_images/contents_images-1621489075322-%EA%B8%88%EC%9D%B4%EC%82%B0%EB%86%8D%EC%9B%90-%EB%B3%B5%EC%88%AD%EC%95%84%EC%99%80%EC%9D%B8-2.png\"></p><p class=\"ql-align-center\"><strong class=\"ql-size-large\">[금이산 복숭아 와인], </strong></p><p class=\"ql-align-center\"><strong class=\"ql-size-large\">어떤 음식과 잘 어울리나요?</strong></p><p class=\"ql-align-center\"><br></p><p class=\"ql-align-center\">강한 단맛을 무겁지 않게 즐기고 복숭아의</p><p class=\"ql-align-center\"><br></p><p class=\"ql-align-center\">싱그러운 향을 생동감 있게 즐기기 위해선</p><p class=\"ql-align-center\"><br></p><p class=\"ql-align-center\"><strong style=\"color: rgb(255, 153, 0);\">시원한 상태</strong>로 마시는 것을 추천해 드립니다.</p><p class=\"ql-align-center\"><br></p><p class=\"ql-align-center\"><br></p><p class=\"ql-align-center\"><br></p><p class=\"ql-align-center\">마실 땐 탄산수와 레몬 슬라이스를 넣어 청량감 있는</p><p class=\"ql-align-center\"><br></p><p class=\"ql-align-center\"><strong style=\"color: rgb(255, 153, 0);\">에이드</strong>로 즐겨도 좋고 <strong style=\"color: rgb(255, 153, 0);\">케이크, 마들렌과 같은 디저트류</strong>와</p><p class=\"ql-align-center\"><br></p><p class=\"ql-align-center\">달콤하고 부드럽게 즐기기에도 좋은데요.</p><p class=\"ql-align-center\"><br></p><p class=\"ql-align-center\"><br></p><p class=\"ql-align-center\"><br></p><p class=\"ql-align-center\">단맛과 산미가 조화로워 입맛을 돋우기 때문에</p><p class=\"ql-align-center\"><br></p><p class=\"ql-align-center\"><strong style=\"color: rgb(255, 153, 0);\">식전주 </strong>또는 식사를 마무리하는 <strong style=\"color: rgb(255, 153, 0);\">디저트 와인</strong>으로</p><p class=\"ql-align-center\"><br></p><p class=\"ql-align-center\">가볍게 즐기시는 걸 추천해 드립니다.</p><p class=\"ql-align-center\"><img src=\"https://sooldamhwa-static-files.s3.ap-northeast-2.amazonaws.com/content_images/contents_images-1621489080958-%EA%B8%88%EC%9D%B4%EC%82%B0%EB%86%8D%EC%9B%90-%EB%B3%B5%EC%88%AD%EC%95%84%EC%99%80%EC%9D%B8-3.png\"></p><p class=\"ql-align-center\"><strong class=\"ql-size-large\">[금이산 복숭아 와인], </strong></p><p class=\"ql-align-center\"><strong class=\"ql-size-large\">알고 마시면 더 맛있어요!</strong></p><p class=\"ql-align-center\"><br></p><p class=\"ql-align-center\">맛이 좋기로 유명한 세종시 복숭아를 60여 곳의</p><p class=\"ql-align-center\"><br></p><p class=\"ql-align-center\">지역 농가에서 수급하여 빚고 있는데요.</p><p class=\"ql-align-center\"><br></p><p class=\"ql-align-center\"><br></p><p class=\"ql-align-center\"><br></p><p class=\"ql-align-center\">잘 익은 세종시 조치원 복숭아만을 선별하여<strong> </strong></p><p class=\"ql-align-center\"><br></p><p class=\"ql-align-center\"><strong style=\"color: rgb(255, 153, 0);\">저온 발효시킨</strong><strong> </strong>와인입니다.</p><p class=\"ql-align-center\"><br></p><p class=\"ql-align-center\"><br></p><p class=\"ql-align-center\"><br></p><p class=\"ql-align-center\"><strong style=\"color: rgb(255, 153, 0);\">인위적인 복숭아향을 사용하지 않아</strong> 자극적이지 않고</p><p class=\"ql-align-center\"><br></p><p class=\"ql-align-center\"><strong style=\"color: rgb(255, 153, 0);\">미세한 필터망</strong> 사용을 통해 복숭아 본연의 풍미를</p><p class=\"ql-align-center\"><br></p><p class=\"ql-align-center\">깔끔하게 경험할 수 있답니다.</p>", "origin_price": 17500, "discount_price": 17500, "is_damhwa_box": 0, "selling_count": 201, "hit_count": 0, "star_rating": "4.9", "status": "sold_out", "star_count": 10, "maker_id": 86, "product_images": [{"id": 5749, "product_id": 352, "image_url": "https://sooldamhwa-static-files.s3.ap-northeast-2.amazonaws.com/admin_contents/origin/1jU3-1620615612711-%EA%B8%88%EC%9D%B4%EC%82%B0%EB%B3%B5%EC%88%AD%EC%95%84%EC%99%80%EC%9D%B8.jpg"}], "product_options": [], "maker": {"id": 86, "name": "금이산농원", "maker_image_url": "https://sooldamhwa-static-files.s3.ap-northeast-2.amazonaws.com/admin_contents/origin/dqVB-1622698743085-guem-ee-san-nong-won.png", "value": 86, "label": "금이산농원", "regular_delivery_price": 4000, "special_delivery_price": 8000, "delivery_note": "2일 이내 배송", "min_total_for_free_delivery": 50000, "official_name": "영농조합법인 금이산농원", "ceo_name": "김영기", "email": "kyg510815@naver.com", "phone_number": "044-863-3478", "address": "충청남도 세종특별자치시 전의면 가느실길 127", "registration_number": "244-81-00399", "report_number": "2017-세종조치원-0010"}, "sool": {"id": 177, "product_id": 352, "sool_category_id": 6, "alcohol_content": "12.0", "volumes": "375ml, 500ml, 750ml", "expire_info": "유통기한 없음", "shipping_note": null, "storage_note": "직사광선을 피하여 건조하고 서늘한 곳 보관", "taste_note": "새콤달콤한 복숭아 과실맛", "anju_note": "달콤한 디저트와 잘 어울려요", "damhwa_note": "세종시 조치원 복숭아만을 선별하여 저온 발효시켜 만든 와인", "taste_standard": "fridge", "sool_distinction": "지역 특산주", "other_note": null, "sweet": 8, "weight": -1, "carbonic": 0, "plain": -1, "acidity": 4, "body": 6, "tannin": 4, "nutty": -1, "richness": -1, "spicy": -1, "bitter": -1, "flavor": -1, "award": "", "sool_category": {"name": "과실주"}, "materials": [{"id": 9, "name": "구연산", "sool_materials": {"id": 24578, "sool_id": 177, "material_id": 9, "created_at": "2021-08-11T23:50:32.000Z", "updated_at": "2021-08-11T23:50:32.000Z", "destroyTime": null}}, {"id": 33, "name": "메타중아황산칼륨", "sool_materials": {"id": 24579, "sool_id": 177, "material_id": 33, "created_at": "2021-08-11T23:50:32.000Z", "updated_at": "2021-08-11T23:50:32.000Z", "destroyTime": null}}, {"id": 42, "name": "복숭아", "sool_materials": {"id": 24580, "sool_id": 177, "material_id": 42, "created_at": "2021-08-11T23:50:32.000Z", "updated_at": "2021-08-11T23:50:32.000Z", "destroyTime": null}}, {"id": 96, "name": "효모", "sool_materials": {"id": 24581, "sool_id": 177, "material_id": 96, "created_at": "2021-08-11T23:50:32.000Z", "updated_at": "2021-08-11T23:50:32.000Z", "destroyTime": null}}, {"id": 233, "name": "과일", "sool_materials": {"id": 24582, "sool_id": 177, "material_id": 233, "created_at": "2021-08-11T23:50:32.000Z", "updated_at": "2021-08-11T23:50:32.000Z", "destroyTime": null}}, {"id": 252, "name": "백설탕", "sool_materials": {"id": 24583, "sool_id": 177, "material_id": 252, "created_at": "2021-08-11T23:50:32.000Z", "updated_at": "2021-08-11T23:50:32.000Z", "destroyTime": null}}], "foods": [{"id": 448, "name": "롤케이크", "image_url": "https://sooldamhwa-static-file.s3.ap-northeast-2.amazonaws.com/603da535326c7_20210302113845.png", "sool_foods": {"id": 12838, "sool_id": 177, "food_id": 448, "created_at": "2021-08-11T23:50:32.000Z", "updated_at": "2021-08-11T23:50:32.000Z", "destroyTime": null}}, {"id": 451, "name": "마들렌", "image_url": "https://sooldamhwa-static-file.s3.ap-northeast-2.amazonaws.com/603da5528d1a7_20210302113914.png", "sool_foods": {"id": 12839, "sool_id": 177, "food_id": 451, "created_at": "2021-08-11T23:50:32.000Z", "updated_at": "2021-08-11T23:50:32.000Z", "destroyTime": null}}, {"id": 463, "name": "광어회", "image_url": "https://sooldamhwa-static-file.s3.ap-northeast-2.amazonaws.com/6058412055818_20210322160256.png", "sool_foods": {"id": 12840, "sool_id": 177, "food_id": 463, "created_at": "2021-08-11T23:50:32.000Z", "updated_at": "2021-08-11T23:50:32.000Z", "destroyTime": null}}]}, "tags": [], "product_info": {"id": 118, "product_id": 352, "product_type": "", "label": "", "producer": "영농조합법인 금이산농원", "location": "세종특별자치시 전의면 가느실길 127", "expiration_info": "직사광선을 피하여 건조하고 서늘한 곳 보관 / 유통기한 없음", "volume": "375ml, 500ml, 750ml", "base_material": "복숭아(국내산) 92.07%, 백설탕 7.8%, 효모 0.02%, 메타중아황산칼륨(산화방지제) 0.01%, 구연산 0.1%, 복숭아/메타중아황산칼륨 함유", "nutrient": "사진 및 상세 설명 확인", "gmo": "해당 사항 없음", "import_note": "해당 사항 없음", "created_at": "2021-05-11T04:14:34.000Z", "updated_at": "2021-05-13T16:16:30.000Z", "destroyTime": null}}}